{
  "chunk": "chunk1",
  "stage1_3_file": "/Users/my/Documents/projects/detectionDeviation/intermediate_results/01_preprocessing/reaPrep/01_extracting/readeonticstagepipeline/rea_with_injections/chunk1/chunk1_stage1_3.json",
  "stage4_output": [
    {
      "id": "REA-01",
      "text": "Upon your request and expression of consent, we collect the following data for the purpose of providing services to you.",
      "actor": "we",
      "modal": "Permissive",
      "action": "collect",
      "action_list": [
        "collect"
      ],
      "object": "your request and expression of consent",
      "temporal": "following data for the purpose of",
      "manner": "",
      "condition": "Upon your request and expression of consent",
      "article": "chunk1",
      "paragraph": "1",
      "source": "hybrid",
      "rea_id": "REA-01",
      "sub_id": "REA-01#1",
      "split_index": "1"
    },
    {
      "id": "REA-01",
      "text": "Your data is not used for any other purposes or shared with third parties.",
      "actor": "Your data",
      "modal": "Prohibited",
      "action": "use",
      "action_list": [
        "use"
      ],
      "object": "any other purposes",
      "temporal": "",
      "manner": "",
      "condition": "",
      "article": "chunk1",
      "paragraph": "1",
      "source": "hybrid",
      "rea_id": "REA-01",
      "sub_id": "REA-01#2",
      "split_index": "2"
    },
    {
      "id": "REA-01",
      "text": "It is removed upon your withdrawal of consent or your request to terminate these services.",
      "actor": "we",
      "modal": "Permissive",
      "action": "remove",
      "action_list": [
        "remove"
      ],
      "object": "your withdrawal of consent or your request to terminate these services",
      "temporal": "upon your withdrawal of consent or",
      "manner": "",
      "condition": "",
      "article": "chunk1",
      "paragraph": "1",
      "source": "hybrid",
      "rea_id": "REA-01",
      "sub_id": "REA-01#3",
      "split_index": "3"
    }
  ]
}